Metadata-Version: 2.1
Name: installify
Version: 0.0.1
Summary: Python installify, Setup File
Author: r4isy
Author-email: r4isy@kenucheck.xyz
